{
    "mode": "default",
    "layout": {
        "text": "right",
        "alignment": "left",
        "mobilealign": "top",
        "columns": [7, 5]
    },
    "style": "dark-text-light-box",
    "variation": {
        "headertext": "small"
    },
    "image": {
        "background": "true",
        "srcDesktop": "img/primary-tout-p1-d7/primary-tout-04-desktop.jpg",
        "srcDesktopHighRes": "img/primary-tout-p1-d7/primary-tout-04-desktop@2x.jpg",
        "srcTablet": "img/primary-tout-p1-d7/primary-tout-04-tablet.jpg",
        "srcTabletHighRes": "img/primary-tout-p1-d7/primary-tout-04-tablet@2x.jpg",
        "srcPhone": "img/primary-tout-p1-d7/primary-tout-04-phone.jpg",
        "srcPhoneHighRes": "img/primary-tout-p1-d7/primary-tout-04-phone@2x.jpg",
        "noscriptsrc": "img/primarytout/primary-tout-04-desktop.jpg",
        "alt": "Lorem ipsum dolor sit amet, consectetur adipisicing elit."
    },
    "headline": "Waterproof MP3 player",
    "body": "Body copy any rate, the popular name for him does not sufficiently distinguish him, since the though a smaller one.",
    "links": [
        {
            "type": "btn",
            "text": "Explore the NEX-6",
            "url": "#"
        }
    ],
    "submodules": []
}
