{
    "tabs": [
        {
            "label": "Featured",
            "slug": "featured",
            "icon": "grid-alt"
        },
        {
            "label": "Cameras",
            "slug": "cameras",
            "icon": "camera"
        },
        {
            "label": "Accessories",
            "slug": "accessories",
            "icon": "dongle"
        },
        {
            "label": "Tab 4",
            "slug": "tab4-fake",
            "icon": "tablet"
        },
        {
            "label": "Tab 5",
            "slug": "tab5-fake",
            "icon": "memory-stick"
        },
        {
            "label": "Tab 6",
            "slug": "tab6-fake",
            "icon": "water-drop"
        },
        {
            "label": "Tab 7",
            "slug": "tab7-fake",
            "icon": "headphones"
        },
        {
            "label": "Tab 8",
            "slug": "tab8-fake",
            "icon": "cd"
        },
        {
            "label": "Tab 9",
            "slug": "tab9-fake",
            "icon": "tv"
        },
        {
            "label": "Tab 10",
            "slug": "tab10-fake",
            "icon": "projector"
        }
    ],
    "featured": {
        "_comments": "name should be unique, as it is used for IDs.",
        "name": "featured-cameras",
        "title": "Featured Cameras",
        "mode": "editorial",
        "layout": "layout1",
        "callout": "See &amp; Compare All Cameras"
    },
    "featured2": {
        "_comments": "name should be unique, as it is used for IDs.",
        "name": "featured-accessories",
        "title": "Featured Accessories",
        "mode": "editorial",
        "layout": "layout2",
        "callout": "See &amp; Compare All Camera Accessories"
    },
    "productCards": {
        "_comments": "name should be unique, as it is used for IDs. galleryName is used in the compare screen.",
        "name": "camera-cards",
        "mode": "detailed",
        "galleryName": "Cyber-shot&reg;",
        "filterSet": [
            {
                "filterGroup" : 1,
                "name": "colors",
                "label": "Colors",
                "type": "color",
                "filters": [
                    {
                        "label": "Black",
                        "value": "black"
                    },
                    {
                        "label": "Silver",
                        "value": "silver"
                    },
                    {
                        "label": "Green",
                        "value": "green"
                    },
                    {
                        "label": "Blue",
                        "value": "blue"
                    },
                    {
                        "label": "White",
                        "value": "white"
                    },
                    {
                        "label": "Red",
                        "value": "red"
                    }
                ]
            },
            {
                "filterGroup" : 3,
                "label": "Best For",
                "name": "group",
                "type": "group",
                "filters": [
                    {
                        "label": "Skating",
                        "description": "Waterproof, shockproof, dustproof, and rugged.",
                        "value": "skating",
                        "icon": "skateboard"
                    },
                    {
                        "label": "Running",
                        "description": "Water resistant, shockproof, and ultra small.",
                        "value": "running",
                        "icon": "runner"
                    },
                    {
                        "label": "Studio",
                        "description": "Music recording, professional quality, best sound.",
                        "value": "studio",
                        "icon": "mic-studio"
                    }
                ]
            },
            {
                "filterGroup" : 1,
                "label": "Megapixels",
                "name": "megapixels",
                "type": "button",
                "filters": [
                    {
                        "label": "14-16",
                        "value": "14-16"
                    },
                    {
                        "label": "16-18",
                        "value": "16-18"
                    },
                    {
                        "label": "18-20",
                        "value": "18-20"
                    },
                    {
                        "label": "20+",
                        "value": "20+"
                    }
                ],
                "help": {
                    "label" : "What&rsquo;s the difference?",
                    "title" : "Higher megapixel count gets you:",
                    "layout" : "2up",
                    "col1" : {
                        "img" : {
                            "src" : "img/cameras/megapixel-print.jpg",
                            "noscriptsrc" : "img/cameras/megapixel-print-desktop.jpg",
                            "alt" : ""
                        },
                        "text" : "Bigger &amp; better quality prints"
                    },
                    "col2" : {
                        "img" : {
                            "src" : "img/cameras/megapixel-crop.png",
                            "noscriptsrc" : "img/cameras/megapixel-crop-desktop.png",
                            "alt" : ""
                        },
                        "text" : "Higher resolution crops"
                    }
                }
            },
            {
                "filterGroup" : 2,
                "label": "Features",
                "name": "features",
                "type": "checkbox",
                "filters": [
                    {
                        "label": "LCD",
                        "value": "lcd",
                        "help": {
                            "title" : "LCD Displays",
                            "layout" : "text-only",
                            "text" : "Derp Derp Derp Derp Derp Derp Derp Derp Derp Derp Derp Derp"
                        }
                    },
                    {
                        "label": "Touchscreen LCD",
                        "value": "touchscreen",
                        "help": {
                            "title" : "LCD Displays",
                            "layout" : "text-only",
                            "text" : "Phase Phase Phase Phase Phase Phase Phase Phase Phase Phase Phase Phase"
                        }
                    },
                    {
                        "label": "Intelligent Sweep Panorama",
                        "value": "panorama",
                        "help": {
                            "title" : "LCD Displays",
                            "layout" : "text-only",
                            "text" : "Programming Programming Programming Programming Programming Programming Programming Programming Programming Programming Programming Programming"
                        }
                    },
                    {
                        "label": "Lightweight",
                        "value": "lightweight",
                        "help": {
                            "title" : "LCD Displays",
                            "layout" : "text-only",
                            "text" : "Sublime Sublime Sublime Sublime Sublime Sublime Sublime Sublime Sublime Sublime Sublime Sublime"
                        }
                    }
                ]
            }
        ],
        "sortSet": [
            {
                "name": "default",
                "label": "Featured"
            },
            {
                "name": "price",
                "label": "Price - high to low",
                "reverse": true
            },
            {
                "name": "price",
                "label": "Price - low to high"
            },
            {
                "name": "popularity",
                "label": "Popularity"
            },
            {
                "name": "rating",
                "label": "Rating",
                "reverse": true
            },
            {
                "name": "release-date",
                "label": "New Products",
                "reverse": true
            }

        ],
        "comparable": [
            {
                "slug": "dimensions",
                "label": "Dimensions"
            },
            {
                "slug": "sensor",
                "label": "Megapixels &amp; Sensor"
            },
            {
                "slug": "bestFor",
                "label": "Best For"
            },
            {
                "slug": "fps",
                "label": "Frames Per Second"
            },
            {
                "slug": "opticalZoom",
                "label": "Optical Zoom"
            },
            {
                "slug": "lensType",
                "label": "Lens Type"
            },
            {
                "slug": "videoRecording",
                "label": "HD Video Recording"
            },
            {
                "slug": "recordingFormat",
                "label": "Recording Format"
            },
            {
                "slug": "sweepPanorama",
                "label": "Sweep Panorama"
            },
            {
                "slug": "waterproof",
                "label": "Water Proof"
            },
            {
                "slug": "lcdScreen",
                "label": "LCD Screen"
            },
            {
                "slug": "3dCapable",
                "label": "3D Capability"
            },
            {
                "slug": "wifiSharing",
                "label": "Wi-Fi Sharing"
            },
            {
                "slug": "gpsTagging",
                "label": "GPS Tagging"
            }
        ],
        "nextLink": "gallery-single2.html"
    },
    "accessories": [
        {
            "title": "Cases, Covers &amp; Straps",
            "callout": "See All 25 Cases, Covers &amp; Straps",
            "subtype" : "casesCoversAndStraps"
        },
        {
            "title": "Batteries &amp; Chargers",
            "callout": "See All 18 Batteries &amp; Chargers",
            "subtype" : "batteriesAndChargers"

        },
        {
            "title": "Tripods &amp; Remotes",
            "subtype" : "tripodsAndRemotes"
        }
    ],
    "submodules": [
        {
            "type": "product.html.jade",
            "data": "product/rx100.json"
        },
        {
            "type": "product.html.jade",
            "data": "product/lens-tout.json"
        },
        {
            "type": "product.html.jade",
            "data": "product/w650.json"
        },
        {
            "type": "product.html.jade",
            "data": "product/tx20.json"
        },
        {
            "type": "product.html.jade",
            "data": "product/hx30.json"
        },
        {
            "type": "product.html.jade",
            "data": "product/hx10.json"
        },
        {
            "type": "product.html.jade",
            "data": "product/w610.json"
        },
        {
            "type": "product.html.jade",
            "data": "product/hx200v.json"
        },
        {
            "type": "product.html.jade",
            "data": "product/wx150.json"
        },
        {
            "type": "product.html.jade",
            "data": "product/rx1.json"
        },
        {
            "type": "product.html.jade",
            "data": "product/battery-charger.json"
        },
        {
            "type": "product.html.jade",
            "data": "product/carrying-case.json"
        },
        {
            "type": "product.html.jade",
            "data": "product/marine-pack.json"
        },
        {
            "type": "product.html.jade",
            "data": "product/summer-promo.json"
        },
        {
            "type": "product.html.jade",
            "data": "product/usb-charger.json"
        },
        {
            "type": "product.html.jade",
            "data": "product/vct-r100.json"
        },
        {
            "type": "product.html.jade",
            "data": "product/memory-card.json"
        },
        {
            "type": "product.html.jade",
            "data": "product/vct-r640.json"
        },
        {
            "type": "product.html.jade",
            "data": "product/carrying-case-LCMCSVHB.json"
        },
        {
            "type": "product.html.jade",
            "data": "product/carrying-case-LCSBBFB.json"
        },
        {
            "type": "product.html.jade",
            "data": "product/camera-case-LCSTWKB.json"
        },
        {
            "type": "product.html.jade",
            "data": "product/carrying-case-LCJRXBB.json"
        },
        {
            "type": "product.html.jade",
            "data": "product/carrying-case-LCJTHFB.json"
        },
        {
            "type": "product.html.jade",
            "data": "product/battery-charger-2.json"
        },
        {
            "type": "product.html.jade",
            "data": "product/cybershot-accessory-kit.json"
        },
        {
            "type": "product.html.jade",
            "data": "product/batteries.json"
        },
        {
            "type": "product.html.jade",
            "data": "product/rechargeable-battery-pack.json"
        },
        {
            "type": "product.html.jade",
            "data": "product/cybershot-wall-charger.json"
        },
        {
            "type": "product.html.jade",
            "data": "product/vct-r100-remote.json"
        }
    ],
    "config": {
        "module_name": "gallery",
        "module_id": "gallery"
    }
}