{
    "type" : "accessory",
    "subtype" : "batteriesAndChargers",
    "featured" : false,
    "label" : false,
    "priority": "",
    "imgSmall": {
        "src" : "img/product/cameras/sml/battery-charger.png",
        "noscriptsrc" : "img/product/cameras/sml/battery-charger-desktop.png",
        "alt": "Battery Charger"
    },
    "img": {
        "src" : "img/product/cameras/med/battery-charger.png",
        "noscriptsrc" : "img/product/cameras/med/battery-charger-desktop.png",
        "alt": "Battery Charger"
    },
    "name": "Battery Charger",
    "price": 49.99
}