{
    "filterSet" : {
        "features" : [ "lcd", "lightweight" ],
        "price" : 369.99,
        "megapixels" : "18-20",
        "popularity" : 77,
        "rating" : 4,
        "release-date" : "2012-11-05T20:13:05.771Z",
        "group" : ["running", "studio"],
        "colors" : ["black"]
    },
    "img" : {
        "src" : "img/cameras/DSCHX30V-frt-med.png",
        "alt" : ""
    },
    "model" : "DSC-HX30/B",
    "name" : "Cyber-shot Digital Camera HX30",
    "rating" : {
        "stars" : 4,
        "reviews" : 10
    },
    "price" : 369.99,
    "meta" : [
        { "name" : "Megapixels", "value" : 18.2 },
        { "name" : "Clear Image Zoom", "value" : "20x/40x" },
        { "name" : "HD Video", "value" : "1080p" }
    ]
}