{
    "config": {
        "module_name": "Editorial",
        "module_id": "editorial"
    },
    "mode": "full-inner",
    "layout": {
        "name": "full-inner-right-75",
        "text": "right",
        "alignment": "left",
        "columns": [7, 5]
    },
    "variation" : {
        "background" : "gray"
    },
    "style": "light-text-dark-box",
    "title": "Travels well",
    "subtitle": "",
    "body": "The pro combines the best features or work and life on the go. It&rsquo;s durable enough to handle the overhead bin and light enough for your carry-on bag. You&rsquo;ll find the best of Sony technology to keep you connected and fully powered when you need it most.",
    "submodules": [
        {
            "type": "image/html/image.jade",
            "data": "packages/pages/data/editorial-layouts-e1/image-e1-fw-vaio-pro-04.json"
        }
    ]
}