{
  "starting_tab_index": "1501",
  "label_tag":{
    "label": "Featured"
  },
  "close_btn":{
    "label": "Close",
    "srcDesktop": "img/universal-nav/close-btn-x.png",
    "srcDesktopHighRes": "img/universal-nav/close-btn-x@2x.png"
  },
  "title":"Sony Sites",
  "all_sites_link": {
    "label": "All Sony Sites",
    "link": "#ALLSITESLINK"
  },
  "primary_columns": [
    {
      "double_tall": "true",
      "features": [
        {
          "caption": "Skyfall Campaign",
          "img":{
            "srcDesktop": "img/universal-nav/feature-full-skyfall-desktop.jpg",
            "srcDesktopHighRes": "img/universal-nav/feature-full-skyfall-desktop@2x.jpg",
            "alt":"Skyfall Campaign"
          },
          "link":"#SKYFALLLINK",
          "featured_flag": "true"
        }
      ]
    },
    {
      "features": [
        {
          "caption": "Sony Mobile",
          "img":{
            "srcDesktop": "img/universal-nav/feature-half-sonymobile-desktop.jpg",
            "srcDesktopHighRes": "img/universal-nav/feature-half-sonymobile-desktop@2x.jpg",
            "alt":"Sony Mobile"
          },
          "link":"#MOBILELINK",
          "featured_flag": "false"
        },
        {
          "caption": "Sony + Google Campaign",
          "img":{
            "srcDesktop": "img/universal-nav/feature-half-sonygoogle-desktop.jpg",
            "srcDesktopHighRes": "img/universal-nav/feature-half-sonygoogle-desktop@2x.jpg",
            "alt":"Sony + Google Campaign"
          },
          "link":"#SONYGOOGLELINK",
          "featured_flag": "false"
        }
      ]
    },
    {
      "features": [
        {
          "caption": "Sony PlayStation",
          "img":{
            "srcDesktop": "img/universal-nav/feature-half-playstation-desktop.jpg",
            "srcDesktopHighRes": "img/universal-nav/feature-half-playstation-desktop@2x.jpg",
            "alt":"Sony PlayStation"
          },
          "link":"#PLAYSTATIONLINK",
          "featured_flag": "false"
        },
        {
          "caption": "Sony Connected World",
          "img":{
            "srcDesktop": "img/universal-nav/feature-half-connected-desktop.jpg",
            "srcDesktopHighRes": "img/universal-nav/feature-half-connected-desktop@2x.jpg",
            "alt":"Sony Connected World"
          },
          "link":"#SONYCONNECTEDLINK",
          "featured_flag": "false"
        }
      ]
    }
  ],
  "secondary_columns": [
    {
      "caption": "Sony Pictures",
      "description": "Movies and television programs from Sony Pictures.",
      "link": "#SONYPICTURESLINK"
    },
    {
      "caption": "Sony Rewards",
      "description": "Exclusive deals on Sony products and content.",
      "link": "#SONYREWARDSLINK"
    },
    {
      "caption": "Sony Online Entertainment",
      "description": "Immersive entertainment for your PC, Tablet and Mobile.",
      "link": "#SONYONLINELINK"
    },
    {
      "caption": "Sony Professional",
      "description": "Broadcast and professional video and audio solutions.",
      "link": "#SONYPROLINK"
    },
    {
      "caption": "Sony Music",
      "description": "Local artists and international superstars of recorded music.",
      "link": "#SONYMUSICLINK"
    },
    {
      "caption": "Reader Store",
      "description": "New releases, page-turning bestsellers and classics.",
      "link": "#READERSTORELINK"
    },
    {
      "caption": "Crackle",
      "description": "Watch hundreds of movies and TV shows online.",
      "link": "#CRACKLELINK"
    }
  ]
}

